{
  "main": {
    "id": "18df6e4bb1006a93",
    "type": "split",
    "children": [
      {
        "id": "fa9c1de0de5c9a5a",
        "type": "tabs",
        "children": [
          {
            "id": "863b202cb4dee9c0",
            "type": "leaf",
            "state": {
              "type": "empty",
              "state": {},
              "icon": "lucide-file",
              "title": "New tab"
            }
          }
        ]
      }
    ],
    "direction": "vertical"
  },
  "left": {
    "id": "b0e75a7bf45c31e7",
    "type": "split",
    "children": [
      {
        "id": "1a97ce28ba1ded36",
        "type": "tabs",
        "children": [
          {
            "id": "3b6791c137d1c216",
            "type": "leaf",
            "state": {
              "type": "file-explorer",
              "state": {
                "sortOrder": "alphabetical",
                "autoReveal": false
              },
              "icon": "lucide-folder-closed",
              "title": "Files"
            }
          },
          {
            "id": "d67b9a8575cf11dd",
            "type": "leaf",
            "state": {
              "type": "search",
              "state": {
                "query": "",
                "matchingCase": false,
                "explainSearch": false,
                "collapseAll": false,
                "extraContext": false,
                "sortOrder": "alphabetical"
              },
              "icon": "lucide-search",
              "title": "Search"
            }
          },
          {
            "id": "180b4fda6e1dd562",
            "type": "leaf",
            "state": {
              "type": "bookmarks",
              "state": {},
              "icon": "lucide-bookmark",
              "title": "Bookmarks"
            }
          },
          {
            "id": "b3889958a5b17040",
            "type": "leaf",
            "state": {
              "type": "notebook-navigator",
              "state": {},
              "icon": "notebook-navigator",
              "title": "Notebook Navigator"
            }
          }
        ],
        "currentTab": 3
      }
    ],
    "direction": "horizontal",
    "width": 621.5
  },
  "right": {
    "id": "1277464457d96220",
    "type": "split",
    "children": [
      {
        "id": "e4941d5cd98d6fcd",
        "type": "tabs",
        "children": [
          {
            "id": "7f9ba6449f667f20",
            "type": "leaf",
            "state": {
              "type": "backlink",
              "state": {
                "collapseAll": false,
                "extraContext": false,
                "sortOrder": "alphabetical",
                "showSearch": false,
                "searchQuery": "",
                "backlinkCollapsed": false,
                "unlinkedCollapsed": true
              },
              "icon": "links-coming-in",
              "title": "Backlinks"
            }
          },
          {
            "id": "339c621c0b5f270a",
            "type": "leaf",
            "state": {
              "type": "outgoing-link",
              "state": {
                "linksCollapsed": false,
                "unlinkedCollapsed": true
              },
              "icon": "links-going-out",
              "title": "Outgoing links"
            }
          },
          {
            "id": "f2d82c7b34a6b80f",
            "type": "leaf",
            "state": {
              "type": "tag",
              "state": {
                "sortOrder": "frequency",
                "useHierarchy": true,
                "showSearch": false,
                "searchQuery": ""
              },
              "icon": "lucide-tags",
              "title": "Tags"
            }
          },
          {
            "id": "90ded1f5f1d04022",
            "type": "leaf",
            "state": {
              "type": "all-properties",
              "state": {
                "sortOrder": "frequency",
                "showSearch": false,
                "searchQuery": ""
              },
              "icon": "lucide-archive",
              "title": "All properties"
            }
          },
          {
            "id": "d5acdd9fad152637",
            "type": "leaf",
            "state": {
              "type": "outline",
              "state": {
                "followCursor": false,
                "showSearch": false,
                "searchQuery": ""
              },
              "icon": "lucide-list",
              "title": "Outline"
            }
          },
          {
            "id": "6813f1948d7531a7",
            "type": "leaf",
            "state": {
              "type": "calendar",
              "state": {},
              "icon": "lucide-ghost",
              "title": "calendar"
            }
          }
        ]
      }
    ],
    "direction": "horizontal",
    "width": 300,
    "collapsed": true
  },
  "left-ribbon": {
    "hiddenItems": {
      "command-palette:Open command palette": false,
      "omnisearch:Omnisearch": false,
      "graph:Open graph view": false,
      "switcher:Open quick switcher": true,
      "obsidian-excalidraw-plugin:New drawing": false,
      "canvas:Create new canvas": false,
      "daily-notes:Open today's daily note": true,
      "templates:Insert template": true,
      "random-note:Open random note": true,
      "bases:Create new base": true,
      "claudian:Open Claudian": false,
      "obsidian-git:Open Git source control": true,
      "tasknotes:Open mini calendar view": true,
      "tasknotes:Open calendar view": false,
      "tasknotes:Open tasks view": true,
      "tasknotes:Open agenda view": true,
      "tasknotes:Open kanban board": false,
      "tasknotes:Open pomodoro timer": true,
      "tasknotes:Open pomodoro statistics": true,
      "tasknotes:Create new task": true,
      "marp:Marp: Open Preview": true,
      "notebook-navigator:Notebook Navigator": true
    }
  },
  "active": "863b202cb4dee9c0",
  "lastOpenFiles": [
    "TaskNotes/Views/kanban-default.base",
    "(WORK) 工作/Meeting/MoM_2026-04-23_iMRO_sentencing_BOM.md",
    "Excalidraw/Excalidraw_2026-04-23_WSI_outstanding_amendment.md",
    "(WORK) 工作/Projects_HAESL/planning_HAESL/proj_BI_induction_WSI/WSI_outstanding_BI.md",
    "(WORK) 工作/Projects_HAESL/planning_HAESL/proj_BI_induction_WSI/map_Induction_WSI_workflow.canvas",
    "Excalidraw/Excalidraw_2026-04-16_.INVEST.md",
    "(WORK) 工作/Meeting/assets/MoM_2026-04-23_iMRO_sentencing_BOM",
    "(WORK) 工作/Meeting/assets/MoM_2026-04-23_iMRO_sentencing_BOM/file-20260423134804756.jpg",
    "(WORK) 工作/Meeting/assets/MoM_2026-04-23_iMRO_sentencing_BOM/file-20260423134804764.jpg",
    "(WORK) 工作/Meeting/assets/MoM_2026-04-23_iMRO_sentencing_BOM/file-20260423134804766.jpg",
    "(IDEAVERSE) 思維系統/2026/April/assets/MoM_2026-04-23_iMRO_sentencing_BOM",
    "TaskNotes/Views/mini-calendar-default.base",
    "TaskNotes/Views/calendar-default.base",
    "TaskNotes/Views/agenda-default.base",
    "(WORK) 工作/Projects_HAESL/proj_digital_streamer/streamer_feedback_review (Task Owner).md",
    "Excalidraw/Excalidraw_2026-04-16_.AI Agent.md"
  ]
}